{
  "elements": [
    {
      "id": 40,
      "name": "FFFF",
      "coordinates": {
        "x": 2.0,
        "y": 2.0
      },
      "creationDate": "2025-04-25T22:57:56.2166768",
      "numberOfParticipants": 3,
      "genre": "BLUES",
      "frontMan": {
        "name": "john",
        "birthday": "2019-02-21",
        "height": 100.0,
        "weight": 120,
        "hairColor": "BLUE"
      }
    },
    {
      "id": 39,
      "name": "ggg",
      "coordinates": {
        "x": 2.0,
        "y": 2.0
      },
      "creationDate": "2025-04-25T22:57:56.1886704",
      "numberOfParticipants": 3,
      "frontMan": {
        "name": "john",
        "birthday": "2019-02-21",
        "weight": 120
      }
    },
    {
      "id": 41,
      "name": "GGGG",
      "coordinates": {
        "x": -2.0,
        "y": -2.0
      },
      "creationDate": "2025-04-25T22:57:56.221678",
      "numberOfParticipants": 3,
      "frontMan": {
        "name": "john",
        "birthday": "2019-02-21",
        "weight": 120
      }
    }
  ]
}